helloworld_deanaz.py
helloworld_deanaz-0.0.3.dist-info/LICENSE.txt
helloworld_deanaz-0.0.3.dist-info/METADATA
helloworld_deanaz-0.0.3.dist-info/WHEEL
helloworld_deanaz-0.0.3.dist-info/top_level.txt
helloworld_deanaz-0.0.3.dist-info/RECORD
