Metadata-Version: 2.1
Name: helloworld-deanaz
Version: 0.0.3
Summary: A package for training and predicting temporal cell
Home-page: https://github.com/user/reponame
Author: Dean Sumner
Author-email: dean.sumner@astrazeneca.net
License: MIT
Download-URL: https://github.com/user/reponame/archive/v_01.tar.gz
Platform: UNKNOWN
Classifier: Programming Language :: Python :: 3.8
Classifier: License :: OSI Approved :: MIT License
Classifier: Operating System :: OS Independent
